tool_create_project/__init__.py
tool_create_project/cli.py
tool_create_project/main.py
tool_create_project/py.typed
tool_create_project-0.1.1.dist-info/METADATA
tool_create_project-0.1.1.dist-info/WHEEL
tool_create_project-0.1.1.dist-info/entry_points.txt
tool_create_project-0.1.1.dist-info/RECORD
